flametracker/UntrackedActionNode.py
flametracker/__init__.py
flametracker/core.py
flametracker/py.typed
flametracker/rendering.py
flametracker/tracking.py
flametracker/types.py
flametracker-0.1.9.dist-info/licenses/LICENSE
flametracker-0.1.9.dist-info/METADATA
flametracker-0.1.9.dist-info/WHEEL
flametracker-0.1.9.dist-info/top_level.txt
flametracker-0.1.9.dist-info/RECORD
