Metadata-Version: 2.4
Name: flametracker
Version: 0.1.9
Summary: A script tracking utility to generate flamegraph
Author-email: Etienne_MR <etienne@etiennemr.fr>
License-Expression: MIT
Project-URL: Homepage, https://github.com/EtienneMR/flametracker
Keywords: flamegraph,profiling,tracking
Requires-Python: >=3.6
License-File: LICENSE
Dynamic: license-file
